MANIFEST.in
README.md
darts.h
pydarts.cpp
pydarts.pyx
setup.py
pydarts.egg-info/PKG-INFO
pydarts.egg-info/SOURCES.txt
pydarts.egg-info/dependency_links.txt
pydarts.egg-info/top_level.txt
test/test_pydarts.py