Metadata-Version: 1.1
Name: pydarts
Version: 1.1.3
Summary: Python binding of Darts
Home-page: https://github.com/jxpress/pydarts
Author: JX PRESS Corp.
Author-email: info@jxpress.net
License: UNKNOWN
Platform: UNKNOWN
Classifier: License :: OSI Approved :: Apache Software License
Classifier: Programming Language :: Cython
Classifier: Programming Language :: Python :: 2
Classifier: Programming Language :: Python :: 3
